meetsms/__init__.py
meetsms/meetsms.py
meetsms/tests/__init__.py
meetsms/tests/test_meetsms.py
MeetSMS-1.3.3.dist-info/LICENSE
MeetSMS-1.3.3.dist-info/METADATA
MeetSMS-1.3.3.dist-info/WHEEL
MeetSMS-1.3.3.dist-info/entry_points.txt
MeetSMS-1.3.3.dist-info/top_level.txt
MeetSMS-1.3.3.dist-info/RECORD
