Metadata-Version: 2.1
Name: MeetSMS
Version: 1.3.3
Summary: Send SMS easily using MeetSMS
Home-page: https://github.com/unique1o1/Meet-SMS
Author: Yunik Maharjan
Author-email: yunik.maharjan@icloud.com
License: MIT
Download-URL: https://github.com/unique1o1/Meet-SMS/archive/v1.3.2.tar.gz
Platform: UNKNOWN
Classifier: Environment :: Console
Classifier: Programming Language :: Python :: 3
Classifier: Programming Language :: Python :: 2.7
Requires-Dist: requests
